[
  {
    "id": 8,
    "titre": "Améliorer l'accessibilité de tous les bâtiments",
    "theme": "Solidarité",
    "statut": "Prioritaire",
    "annee": 2028,
    "budget": 0,
    "resume": "Accessibilité PMR",
    "description": "",
    "importance": 3,
    "chiffres": []
  },
  {
    "id": 10,
    "titre": "Rendre la Maison de Santé pleinement opérationnelle",
    "theme": "Santé",
    "statut": "Programmé",
    "annee": 2027,
    "budget": 0,
    "resume": "Accès aux soins",
    "description": "",
    "importance": 2,
    "chiffres": []
  },
  {
    "id": 16,
    "titre": "Pérenniser les festivals et événements",
    "theme": "Culture",
    "statut": "Programmé",
    "annee": 2026,
    "budget": 0,
    "resume": "Animation culturelle",
    "description": "",
    "importance": 2,
    "chiffres": []
  },
  {
    "id": 18,
    "titre": "Soutenir les associations culturelles",
    "theme": "Culture",
    "statut": "Programmé",
    "annee": 2026,
    "budget": 0,
    "resume": "Vie associative",
    "description": "",
    "importance": 1,
    "chiffres": []
  },
  {
    "id": 21,
    "titre": "Projet en cours de conception",
    "theme": "Économie",
    "statut": "Programmé",
    "annee": 2027,
    "budget": 0,
    "resume": "Tourisme",
    "description": "",
    "importance": 1,
    "image": "",
    "images": [],
    "chiffres": [],
    "chronologie": [],
    "documents": [],
    "details": "",
    "sources": [],
    "lien_source": []
  },
  {
    "id": 22,
    "titre": "Achever le maillage de vidéoprotection",
    "theme": "Tranquillité",
    "statut": "Programmé",
    "annee": 2027,
    "budget": 0,
    "resume": "Vidéoprotection",
    "description": "",
    "importance": 2,
    "chiffres": []
  },
  {
    "id": 23,
    "titre": "Déployer l'éclairage intelligent",
    "theme": "Tranquillité",
    "statut": "Programmé",
    "annee": 2028,
    "budget": 0,
    "resume": "Éclairage public",
    "description": "",
    "importance": 1,
    "chiffres": []
  },
  {
    "id": 24,
    "titre": "Renforcer la médiation de proximité",
    "theme": "Tranquillité",
    "statut": "Programmé",
    "annee": 2026,
    "budget": 0,
    "resume": "Médiation",
    "description": "",
    "importance": 1,
    "chiffres": []
  },
  {
    "id": 32,
    "titre": "Instaurer des correspondants de quartier",
    "theme": "Tranquillité",
    "statut": "Programmé",
    "annee": 2026,
    "budget": 0,
    "resume": "Démocratie de proximité",
    "description": "",
    "importance": 1,
    "chiffres": []
  },
  {
    "id": 33,
    "titre": "Renforcer la transparence (open data)",
    "theme": "Démocratie locale",
    "statut": "Programmé",
    "annee": 2027,
    "budget": 0,
    "resume": "Transparence",
    "description": "",
    "importance": 1,
    "chiffres": []
  },
  {
    "id": 34,
    "titre": "Le maire siègera personnellement aux conseils métropolitains",
    "theme": "Métropole",
    "statut": "Programmé",
    "annee": 2026,
    "budget": 0,
    "resume": "Présence métropolitaine",
    "description": "",
    "importance": 2,
    "chiffres": []
  },
  {
    "id": 35,
    "titre": "Porter la voix de Vizille (transports, PLUi, eau)",
    "theme": "Métropole",
    "statut": "Programmé",
    "annee": 2026,
    "budget": 0,
    "resume": "Défense des intérêts",
    "description": "",
    "importance": 1,
    "chiffres": []
  },
  {
    "id": 36,
    "titre": "Défendre une juste répartition des dotations Sud Métropole",
    "theme": "Métropole",
    "statut": "Programmé",
    "annee": 2026,
    "budget": 0,
    "resume": "Équité territoriale",
    "description": "",
    "importance": 1,
    "chiffres": []
  },
  {
    "id": 101,
    "titre": "Objectif 1 - Mobilités structurantes",
    "theme": "Mobilités",
    "statut": "Étude",
    "annee": null,
    "budget": 0,
    "resume": "Explorer toutes les solutions - long terme",
    "description": "Améliorer les liaisons vers l'agglomération et la vallée : bus, navettes, covoiturage, parkings relais, câble, rail.",
    "importance": 3,
    "chiffres": [],
    "tags": [
      "Connexion",
      "Alternatives",
      "Long terme"
    ],
    "slogan": "Relier • Diversifier • Anticiper",
    "enjeux": [
      "Réduire la dépendance à la voiture individuelle",
      "Offrir des alternatives crédibles aux heures de pointe",
      "Anticiper les besoins futurs du bassin de vie"
    ],
    "axes_action": [
      "Navettes adaptées aux horaires pendulaires",
      "Covoiturage et parkings relais identifiés",
      "Scénarios transport par câble (long terme)",
      "Réflexion sur la solution ferroviaire"
    ],
    "indicateurs": [
      "Études engagées",
      "Partenaires mobilisés",
      "Usage des alternatives"
    ],
    "vision": "Aucune hypothèse n'est écartée pour connecter Vizille au territoire.",
    "numero": "1/7",
    "image": "images/objectifs/objectif_1.png"
  },
  {
    "id": 102,
    "titre": "Objectif 2 - Renforcer les mobilités cyclables",
    "theme": "Mobilités",
    "statut": "Programmé",
    "annee": 2027,
    "budget": 0,
    "resume": "Vizille, cœur du maillage cycliste",
    "description": "Liaisons vers Grenoble, Oisans, Uriage et Matheysine. Réseau continu, lisible et sécurisé.",
    "importance": 3,
    "chiffres": [],
    "tags": [
      "Tranquillité",
      "Sécurité",
      "Mobilités"
    ],
    "slogan": "Relier • Sécuriser • Rendre lisible",
    "enjeux": [
      "Sécuriser les trajets du quotidien",
      "Relier quartiers et équipements",
      "Favoriser une pratique familiale et intergénérationnelle"
    ],
    "axes_action": [
      "Consolider l'axe du Chemin des Murs",
      "Assurer la liaison centre ↔ Péage",
      "Traiter discontinuités et points de conflit",
      "Jalonnement cohérent • Cohabitation des usages"
    ],
    "indicateurs": [
      "Continuités renforcées",
      "Points dangereux traités",
      "Retours d'usagers"
    ],
    "vision": "Un réseau cyclable continu, de quartier à quartier, de vallée à montagne.",
    "numero": "2/7",
    "image": "images/objectifs/objectif_2.png"
  },
  {
    "id": 103,
    "titre": "Objectif 3 - Sécuriser les usagers vulnérables",
    "theme": "Mobilités",
    "statut": "Prioritaire",
    "annee": 2026,
    "budget": 0,
    "resume": "Priorité aux piétons, enfants, seniors, PMR",
    "description": "Traversées sûres, abords d'écoles protégés, accessibilité renforcée pour tous.",
    "importance": 3,
    "chiffres": [],
    "tags": [
      "Sécurité",
      "Accessibilité",
      "Confort"
    ],
    "slogan": "Protéger • Faciliter • Rassurer",
    "enjeux": [
      "Réduire les situations à risque",
      "Améliorer l'accessibilité et le confort de marche",
      "Renforcer le sentiment de sécurité"
    ],
    "axes_action": [
      "Sécuriser les traversées piétonnes",
      "Protéger les abords d'écoles",
      "Améliorer les cheminements accessibles",
      "Rendre les carrefours plus lisibles",
      "Apaiser les vitesses sur secteurs sensibles"
    ],
    "indicateurs": [
      "Points sensibles traités",
      "Qualité des cheminements",
      "Retours usagers"
    ],
    "vision": "Des déplacements sûrs et accessibles pour tous, à chaque âge de la vie.",
    "numero": "3/7",
    "image": "images/objectifs/objectif_3.png"
  },
  {
    "id": 104,
    "titre": "Objectif 4 - Apaiser la circulation",
    "theme": "Mobilités",
    "statut": "Programmé",
    "annee": 2026,
    "budget": 0,
    "resume": "Protéger les quartiers habités",
    "description": "Réduire les nuisances du transit : bruit, vitesses excessives, à-coups de circulation.",
    "importance": 2,
    "chiffres": [],
    "tags": [
      "Tranquillité",
      "Cadre de vie",
      "Sécurité"
    ],
    "slogan": "Ralentir • Protéger • Fluidifier",
    "enjeux": [
      "Réduire vitesses et nuisances sonores",
      "Limiter les reports en rues résidentielles",
      "Rendre la circulation plus prévisible"
    ],
    "axes_action": [
      "Identifier les secteurs exposés au transit",
      "Mettre en œuvre des mesures progressives",
      "Assurer la cohérence avec le plan de circulation",
      "Suivre et ajuster selon les retours"
    ],
    "indicateurs": [
      "Vitesses constatées",
      "Perception des nuisances",
      "Reports de trafic"
    ],
    "vision": "Des quartiers protégés du transit, pour une vie quotidienne apaisée.",
    "numero": "4/7",
    "image": "images/objectifs/objectif_4.png"
  },
  {
    "id": 105,
    "titre": "Objectif 5 - Organiser les flux",
    "theme": "Mobilités",
    "statut": "Étude",
    "annee": 2026,
    "budget": 0,
    "resume": "Un plan de circulation lisible",
    "description": "Clarifier les itinéraires, hiérarchiser les axes, réduire détours et conflits d'usages.",
    "importance": 2,
    "chiffres": [],
    "tags": [
      "Lisibilité",
      "Hiérarchie",
      "Fluidité"
    ],
    "slogan": "Clarifier • Hiérarchiser • Simplifier",
    "enjeux": [
      "Mieux se déplacer dans la commune",
      "Réduire le transit inutile en centre-ville",
      "Limiter les reports dans les quartiers"
    ],
    "axes_action": [
      "Comptages aux points clés",
      "Hiérarchisation des axes (transit / desserte / apaisé)",
      "Clarification signalisation et carrefours",
      "Tester puis déployer progressivement"
    ],
    "indicateurs": [
      "Répartition des flux",
      "Vitesses constatées",
      "Retours d'usage"
    ],
    "vision": "Un plan lisible pour des déplacements simples et cohérents.",
    "numero": "5/7",
    "image": "images/objectifs/objectif_5.png"
  },
  {
    "id": 106,
    "titre": "Objectif 6 - Centre-ville et espaces partagés",
    "theme": "Mobilités",
    "statut": "Étude",
    "annee": 2027,
    "budget": 0,
    "resume": "Apaiser et dynamiser le cœur de ville",
    "description": "Cheminements piétons confortables, espaces partagés lisibles, connexion marché ↔ château.",
    "importance": 3,
    "chiffres": [],
    "tags": [
      "Convivialité",
      "Commerce",
      "Patrimoine"
    ],
    "slogan": "Vivre • Partager • Relier",
    "enjeux": [
      "Améliorer la qualité de vie au centre-ville",
      "Renforcer l'attractivité commerciale",
      "Réduire les conflits d'usage"
    ],
    "axes_action": [
      "Identifier les secteurs à requalifier",
      "Déployer des espaces partagés (20 km/h)",
      "Renforcer les continuités piétonnes",
      "Améliorer la liaison marché → château"
    ],
    "indicateurs": [
      "Fréquentation",
      "Retours commerçants/habitants",
      "Qualité perçue"
    ],
    "vision": "Un centre-ville apaisé, vivant et connecté à son patrimoine.",
    "numero": "6/7",
    "image": "images/objectifs/objectif_6.png"
  },
  {
    "id": 107,
    "titre": "Objectif 7 - Feu de Jarrie (PPRT)",
    "theme": "Mobilités",
    "statut": "Prioritaire",
    "annee": 2026,
    "budget": 0,
    "resume": "Rétablir un fonctionnement adapté",
    "description": "Régulation conforme à la vocation du feu : déclenchée uniquement en cas de congestion avérée.",
    "importance": 3,
    "chiffres": [],
    "tags": [
      "Régulation",
      "Bouchons",
      "Fluidité"
    ],
    "slogan": "Analyser • Adapter • Fluidifier",
    "enjeux": [
      "Réduire les temps de trajet quotidiens",
      "Éviter les bouchons récurrents aux heures de pointe",
      "Assurer une régulation dynamique et proportionnée"
    ],
    "axes_action": [
      "Demander les données de fonctionnement à la DREAL",
      "Réviser le paramétrage du feu",
      "Porter le sujet avec les partenaires (Département, Métro)",
      "Mettre en cohérence avec les alternatives de mobilité"
    ],
    "indicateurs": [
      "Temps de parcours",
      "Durée des phases",
      "Retours usagers"
    ],
    "vision": "Transparence des données, régulation adaptée, bouchons réduits.",
    "numero": "7/7",
    "image": "images/objectifs/objectif_7.png"
  }
]